voter.v
module voter(I, O);

input [3:0] I;
output [3:1] O;
reg [3:1] O;

always@ (I)
begin
    case(I)
        //反對
        4'b0000, 4'b0001, 4'b0010, 4'b0100, 4'b1000:
            O = 3'b001;

        //平手
        4'b0011, 4'b0101, 4'b0110, 4'b1001, 4'b1010, 4'b1100:
            O = 3'b010;

        //贊成
        4'b0111, 4'b1011, 4'b1101, 4'b1110, 4'b1111:
            O = 3'b100;
        default:
            O = 3'b000;
    endcase
end

endmodule

voter_tb.v
module voter_tb;
reg [3:0] I_tb;
wire [3:1] O_tb;

initial
begin
    $dumpfile("voter.vcd");
    $dumpvars(0, v);
    #10 I_tb = 4'b0000;
    #10 I_tb = 4'b0001;
    #10 I_tb = 4'b0010;
    #10 I_tb = 4'b0011;
    #10 I_tb = 4'b0100;
    #10 I_tb = 4'b0101;
    #10 I_tb = 4'b0110;
    #10 I_tb = 4'b0111;
    #10 I_tb = 4'b1000;
    #10 I_tb = 4'b1001;
    #10 I_tb = 4'b1010;
    #10 I_tb = 4'b1011;
    #10 I_tb = 4'b1100;
    #10 I_tb = 4'b1101;
    #10 I_tb = 4'b1110;
    #10 I_tb = 4'b1111;
    #10 $finish;
end

voter v(I_tb, O_tb);

endmodule

voter.vcd
$date
	Fri Apr 08 15:11:46 2022
$end
$version
	Icarus Verilog
$end
$timescale
	1s
$end
$scope module voter_tb $end
$scope module v $end
$var wire 4 ! I [3:0] $end
$var reg 3 " O [3:1] $end
$upscope $end
$upscope $end
$enddefinitions $end
#0
$dumpvars
bx "
bx !
$end
#10
b1 "
b0 !
#20
b1 !
#30
b10 !
#40
b10 "
b11 !
#50
b1 "
b100 !
#60
b10 "
b101 !
#70
b110 !
#80
b100 "
b111 !
#90
b1 "
b1000 !
#100
b10 "
b1001 !
#110
b1010 !
#120
b100 "
b1011 !
#130
b10 "
b1100 !
#140
b100 "
b1101 !
#150
b1110 !
#160
b1111 !
